odd_or_even7/__init__.py
odd_or_even7/checker.py
odd_or_even7-0.0.1.dist-info/licenses/LICENSE
odd_or_even7-0.0.1.dist-info/METADATA
odd_or_even7-0.0.1.dist-info/WHEEL
odd_or_even7-0.0.1.dist-info/top_level.txt
odd_or_even7-0.0.1.dist-info/RECORD
